keyvault_llm/__init__.py
keyvault_llm/_version.py
keyvault_llm/client.py
keyvault_llm/server.py
keyvault_llm/tests/__init__.py
keyvault_llm/tests/test_client.py
keyvault_llm-0.1.4.dev0.dist-info/LICENSE
keyvault_llm-0.1.4.dev0.dist-info/METADATA
keyvault_llm-0.1.4.dev0.dist-info/WHEEL
keyvault_llm-0.1.4.dev0.dist-info/entry_points.txt
keyvault_llm-0.1.4.dev0.dist-info/top_level.txt
keyvault_llm-0.1.4.dev0.dist-info/RECORD
