Metadata-Version: 2.1
Name: keyvault-llm
Version: 0.1.4.dev0
Summary: A simple key management system for development environments
Home-page: https://github.com/yourusername/keyvault
Author: Lorenzo Toscano
Author-email: Lorenzo Toscano <lorenzo.toscano@gmail.com>
License: MIT License
Keywords: key management,development,security
Classifier: Programming Language :: Python :: 3
Classifier: License :: OSI Approved :: MIT License
Classifier: Operating System :: OS Independent
Requires-Python: >=3.7
License-File: LICENSE
Requires-Dist: flask
Requires-Dist: requests
Requires-Dist: waitress
